dpncy/__init__.py
dpncy/__main__.py
dpncy/activator.py
dpncy/cli.py
dpncy/core.py
dpncy/demo.py
dpncy/loader.py
dpncy/package_meta_builder.py
dpncy/stress_test.py
dpncy-1.1.1.dist-info/licenses/LICENSE
dpncy-1.1.1.dist-info/METADATA
dpncy-1.1.1.dist-info/WHEEL
dpncy-1.1.1.dist-info/entry_points.txt
dpncy-1.1.1.dist-info/top_level.txt
dpncy-1.1.1.dist-info/RECORD
