Metadata-Version: 2.4
Name: dpncy
Version: 1.1.1
Summary: The Intelligent Python Dependency Resolver
Author-email: minds3t <patrickryankenneth@gmail.com>
License: MIT
Project-URL: Homepage, https://github.com/patrickryankenneth/dpncy
Classifier: Development Status :: 5 - Production/Stable
Classifier: Intended Audience :: Developers
Classifier: License :: OSI Approved :: MIT License
Classifier: Operating System :: OS Independent
Classifier: Programming Language :: Python :: 3
Classifier: Topic :: Software Development :: Build Tools
Requires-Python: >=3.11
License-File: LICENSE
Requires-Dist: redis
Requires-Dist: packaging
Requires-Dist: requests
Dynamic: license-file
